[
  {
    "restaurant_name":"101. Eli Büyük Şadin Usta",
    "user_name":"Ölümcül O",
    "user_profile_link":"https:\/\/www.tripadvisor.com.tr\/Profile\/_l_mc_lo2024",
    "rating":1,
    "visit_date":"Eyl 2024",
    "travel_type":"Aile",
    "review_title":"Ölümcül O",
    "review_text":"yemege ailemle gittim gerçekten rezalet hijyen sıfır pislik içinde heryer yemekler igrenç sadin bey el yıkama yerinde bulaşık yıkıyo elimizi yıkıyamıyoruz musade bile vermiyor gittigimize pişman olduk",
    "value_rating":0,
    "service_rating":0,
    "food_rating":0,
    "atmosphere_rating":0,
    "helpful_vote_count":0
  },
  {
    "restaurant_name":"101. Eli Büyük Şadin Usta",
    "user_name":"ABDULLAH ADEM A",
    "user_profile_link":"https:\/\/www.tripadvisor.com.tr\/Profile\/ABDULLAHADEMA",
    "rating":4,
    "visit_date":"Tem 2024",
    "travel_type":"Aile",
    "review_title":"ABDULLAH ADEM A",
    "review_text":"Birecik Çarşı Merkezi Sokağında bulunan iki katlı Temiz Buz gibi Kilimalı Mekan . İlgi Güzel Servis Güzel \nBalcan kebap Güzel biraz yanmış ama Eti çok az yeterli değil . Bireciğin orijinal meşhur Balcanı Gerçekten Çok güzel . \nHaşhaşlı Kebapda güzel fakat benim tercihim Balcan kebap Olur . \nAyran sürahi ve buz gibi güzel . \nFiyat 1 Balcan kebap \n2 Şiş haşhaşlı \nSürahi ayran taze meze Sunum 550 TL kart geçiyor . \nBalcan kebap etini artırmalılar Ve yakmadan servis edilirse güzel olur \n10\/8Puan alan bir Mekan",
    "value_rating":0,
    "service_rating":0,
    "food_rating":0,
    "atmosphere_rating":0,
    "helpful_vote_count":33
  }
]